cystem.py
cystem-0.1.0.dist-info/METADATA
cystem-0.1.0.dist-info/WHEEL
cystem-0.1.0.dist-info/RECORD
