Metadata-Version: 2.1
Name: Cystem
Version: 0.1.0
Summary: A Package Manager and build for C++ / C
License: GNU
Author: NightProg
Requires-Python: >=3.12,<4.0
Classifier: License :: Other/Proprietary License
Classifier: Programming Language :: Python :: 3
Classifier: Programming Language :: Python :: 3.12
Requires-Dist: click (>=8.1.7,<9.0.0)
Requires-Dist: lark (>=1.1.9,<2.0.0)
